omicronscala/__init__.py
omicronscala/_methods.py
omicronscala/_scala.py
omicronscala/_version.py
omicronscala-0.3.2.dist-info/LICENSE
omicronscala-0.3.2.dist-info/METADATA
omicronscala-0.3.2.dist-info/WHEEL
omicronscala-0.3.2.dist-info/top_level.txt
omicronscala-0.3.2.dist-info/RECORD
