Metadata-Version: 2.1
Name: omicronscala
Version: 0.3.2
Summary: A python package to read and parse .par files from Omicron.
Home-page: https://gitlab.com/mpanighel/omicronscala
Author: Mirco Panighel
Author-email: panighel@iom.cnr.it
License: MIT
Platform: UNKNOWN
Classifier: Development Status :: 2 - Pre-Alpha
Classifier: Intended Audience :: Developers
Classifier: Natural Language :: English
Classifier: Programming Language :: Python :: 3
Classifier: License :: OSI Approved :: MIT License
Classifier: Operating System :: OS Independent
Requires-Python: >=3.5
Requires-Dist: numpy
